dashboard/__init__.py
dashboard/dashboard.py
dashboard/st_script.py
optimization_dashboard-0.0.1.dist-info/LICENSE
optimization_dashboard-0.0.1.dist-info/METADATA
optimization_dashboard-0.0.1.dist-info/WHEEL
optimization_dashboard-0.0.1.dist-info/top_level.txt
optimization_dashboard-0.0.1.dist-info/RECORD
