Metadata-Version: 2.1
Name: optimization-dashboard
Version: 0.0.1
Summary: 
Home-page: https://github.com/SimonBlanke/optimization-dashboard
Author: Simon Blanke
Author-email: simon.blanke@yahoo.com
License: MIT
Keywords: optimization
Platform: UNKNOWN
Classifier: Programming Language :: Python :: 3
Classifier: Programming Language :: Python :: 3.5
Classifier: Programming Language :: Python :: 3.6
Classifier: Programming Language :: Python :: 3.7
Classifier: License :: OSI Approved :: MIT License
Classifier: Operating System :: OS Independent
Classifier: Topic :: Scientific/Engineering :: Information Analysis
Classifier: Topic :: Scientific/Engineering :: Mathematics
Classifier: Topic :: Software Development :: Libraries :: Python Modules
Classifier: Intended Audience :: Developers
Classifier: Intended Audience :: Information Technology
Classifier: Intended Audience :: Science/Research
Requires-Dist: numpy
Requires-Dist: pandas
Requires-Dist: matplotlib
Requires-Dist: streamlit
Requires-Dist: plotly
Requires-Dist: hiplot
